django_aetos/__init__.py
django_aetos/app_settings.py
django_aetos/apps.py
django_aetos/signals.py
django_aetos/urls.py
django_aetos/views.py
django_aetos/templates/metrics/export.txt
django_aetos-0.3.0.dist-info/METADATA
django_aetos-0.3.0.dist-info/WHEEL
django_aetos-0.3.0.dist-info/licenses/LICENSE.txt
django_aetos-0.3.0.dist-info/RECORD
