Metadata-Version: 2.3
Name: django_aetos
Version: 0.3.0
Summary: Export Django monitoring metrics for prometheus.io
Project-URL: Homepage, https://github.com/uberspace/django-aetos
Project-URL: Issues, https://github.com/uberspace/django-aetos/issues
Author-email: "uberspace.de" <hallo@uberspace.de>
Maintainer-email: "uberspace.de" <hallo@uberspace.de>
License: Copyright (c) 2023 uberspace.de
License-File: LICENSE.txt
Keywords: exporter,metrics,prometheus
Classifier: Development Status :: 4 - Beta
Classifier: Programming Language :: Python
Requires-Python: >=3.9
